pybitgetapi/__init__.py
pybitgetapi/sample.py
python_bitget_api-3.3.5.dist-info/LICENSE
python_bitget_api-3.3.5.dist-info/METADATA
python_bitget_api-3.3.5.dist-info/WHEEL
python_bitget_api-3.3.5.dist-info/top_level.txt
python_bitget_api-3.3.5.dist-info/RECORD
