Metadata-Version: 2.1
Name: python-bitget-api
Version: 3.3.5
Summary: bitget python wrapper with rest API, websocket API.
Home-page: https://github.com/cuongitl/python-bitget
Author: Cuongitl
Author-email: mrcuongit@live.com
Classifier: Programming Language :: Python :: 3
Classifier: License :: OSI Approved :: MIT License
Classifier: Operating System :: OS Independent
Requires-Python: >=3.6
License-File: LICENSE
